libvcell/__init__.py
libvcell/_internal/__init__.py
libvcell/_internal/native_calls.py
libvcell/_internal/native_utils.py
libvcell/lib/libvcell.dll
libvcell/model_utils.py
libvcell/py.typed
libvcell/solver_utils.py
libvcell-0.0.13.dist-info/LICENSE
libvcell-0.0.13.dist-info/METADATA
libvcell-0.0.13.dist-info/WHEEL
libvcell-0.0.13.dist-info/RECORD
