Metadata-Version: 2.3
Name: libvcell
Version: 0.0.13
Summary: This is a python package which wraps a subset of VCell Java code as a native python package.
Author: Jim Schaff
Author-email: schaff@uchc.edu
Requires-Python: >=3.11,<4.0
Classifier: Programming Language :: Python :: 3
Classifier: Programming Language :: Python :: 3.11
Classifier: Programming Language :: Python :: 3.12
Classifier: Programming Language :: Python :: 3.13
Requires-Dist: pydantic (>=2.10.6,<3.0.0)
Project-URL: Documentation, https://virtualcell.github.io/libvcell/
Project-URL: Repository, https://github.com/virtualcell/libvcell
